pytorch_model_summary/__init__.py
pytorch_model_summary/hierarchical_summary.py
pytorch_model_summary/model_summary.py
pytorch_model_summary-0.1.2.dist-info/LICENSE
pytorch_model_summary-0.1.2.dist-info/METADATA
pytorch_model_summary-0.1.2.dist-info/WHEEL
pytorch_model_summary-0.1.2.dist-info/top_level.txt
pytorch_model_summary-0.1.2.dist-info/RECORD
