Metadata-Version: 2.1
Name: pytorch-model-summary
Version: 0.1.2
Summary: It is a Keras style model.summary() implementation for PyTorch
Home-page: https://github.com/amarczew/pytorch_model_summary
Author: Alison Marczewski
Author-email: alison.marczewski@gmail.com
License: MIT
Keywords: pytorch model summary model.summary() keras
Platform: UNKNOWN
Requires-Python: >=3.6
Requires-Dist: tqdm
Requires-Dist: torch
Requires-Dist: numpy
